libraryArsein/An_Wb.py
libraryArsein/Arsein.py
libraryArsein/Cliob.py
libraryArsein/__init__.py
libraryArsein/encryption.py
libraryArsein-4.2.5.dist-info/LICENCE
libraryArsein-4.2.5.dist-info/METADATA
libraryArsein-4.2.5.dist-info/WHEEL
libraryArsein-4.2.5.dist-info/top_level.txt
libraryArsein-4.2.5.dist-info/RECORD
